shardeumexplorer/__init__.py
shardeumexplorer/shardeumexplorer.py
py_shardeum_explorer-0.0.3.dist-info/LICENSE.md
py_shardeum_explorer-0.0.3.dist-info/METADATA
py_shardeum_explorer-0.0.3.dist-info/WHEEL
py_shardeum_explorer-0.0.3.dist-info/top_level.txt
py_shardeum_explorer-0.0.3.dist-info/RECORD
